jax_soft_robot_modelling/__init__.py
jax_soft_robot_modelling/integration.py
jax_soft_robot_modelling/simple.py
jax_soft_robot_modelling/symbolic_derivation/__init__.py
jax_soft_robot_modelling/symbolic_derivation/pendulum.py
jax_soft_robot_modelling/systems/__init__.py
jax_soft_robot_modelling-0.0.1.dist-info/LICENSE.txt
jax_soft_robot_modelling-0.0.1.dist-info/METADATA
jax_soft_robot_modelling-0.0.1.dist-info/WHEEL
jax_soft_robot_modelling-0.0.1.dist-info/top_level.txt
jax_soft_robot_modelling-0.0.1.dist-info/RECORD
