Metadata-Version: 2.1
Name: jax-soft-robot-modelling
Version: 0.0.1
Summary: Kinematic and dynamic models of continuum and articulated soft robots.
Author-email: Maximilian Stölzle <maximilian@stoelzle.ch>
Maintainer-email: Maximilian Stölzle <maximilian@stoelzle.ch>
License: Copyright (c) 2016 The Python Packaging Authority (PyPA)
Project-URL: Homepage, https://github.com/tud-cor-sr/jax-soft-robot-modelling
Project-URL: Bug Reports, https://github.com/tud-cor-sr/jax-soft-robot-modelling/issues
Project-URL: Source, https://github.com/tud-cor-sr/jax-soft-robot-modelling
Keywords: JAX,Soft Robots,Kinematics,Dynamics
Classifier: Development Status :: 3 - Alpha
Classifier: Intended Audience :: Developers
Classifier: Topic :: Software Development :: Build Tools
Classifier: License :: OSI Approved :: MIT License
Classifier: Programming Language :: Python :: 3
Classifier: Programming Language :: Python :: 3.7
Classifier: Programming Language :: Python :: 3.8
Classifier: Programming Language :: Python :: 3.9
Classifier: Programming Language :: Python :: 3.10
Classifier: Programming Language :: Python :: 3.11
Classifier: Programming Language :: Python :: 3 :: Only
Requires-Python: >=3.7
License-File: LICENSE.txt
Requires-Dist: diffrax
Requires-Dist: jax
Requires-Dist: numpy
Requires-Dist: peppercorn
Requires-Dist: sympy
Provides-Extra: dev
Requires-Dist: check-manifest ; extra == 'dev'
Provides-Extra: test
Requires-Dist: coverage ; extra == 'test'
